ee/LICENSE
ee/README.md
ee/__init__.py
ee/key.pub.pem
ee/validate.py
lilypad/__init__.py
lilypad/_configure.py
lilypad/exceptions.py
lilypad/generations.py
lilypad/message_chunk.py
lilypad/messages.py
lilypad/spans.py
lilypad/stream.py
lilypad/tools.py
lilypad/traces.py
lilypad/_opentelemetry/__init__.py
lilypad/_opentelemetry/_utils.py
lilypad/_opentelemetry/_opentelemetry_anthropic/__init__.py
lilypad/_opentelemetry/_opentelemetry_anthropic/patch.py
lilypad/_opentelemetry/_opentelemetry_anthropic/utils.py
lilypad/_opentelemetry/_opentelemetry_azure/__init__.py
lilypad/_opentelemetry/_opentelemetry_azure/patch.py
lilypad/_opentelemetry/_opentelemetry_azure/utils.py
lilypad/_opentelemetry/_opentelemetry_bedrock/__init__.py
lilypad/_opentelemetry/_opentelemetry_bedrock/patch.py
lilypad/_opentelemetry/_opentelemetry_bedrock/utils.py
lilypad/_opentelemetry/_opentelemetry_google_genai/__init__.py
lilypad/_opentelemetry/_opentelemetry_google_genai/patch.py
lilypad/_opentelemetry/_opentelemetry_google_genai/utils.py
lilypad/_opentelemetry/_opentelemetry_google_generative_ai/__init__.py
lilypad/_opentelemetry/_opentelemetry_google_generative_ai/patch.py
lilypad/_opentelemetry/_opentelemetry_google_generative_ai/utils.py
lilypad/_opentelemetry/_opentelemetry_mistral/__init__.py
lilypad/_opentelemetry/_opentelemetry_mistral/patch.py
lilypad/_opentelemetry/_opentelemetry_mistral/utils.py
lilypad/_opentelemetry/_opentelemetry_openai/__init__.py
lilypad/_opentelemetry/_opentelemetry_openai/patch.py
lilypad/_opentelemetry/_opentelemetry_openai/utils.py
lilypad/_opentelemetry/_opentelemetry_outlines/__init__.py
lilypad/_opentelemetry/_opentelemetry_outlines/patch.py
lilypad/_opentelemetry/_opentelemetry_outlines/utils.py
lilypad/_opentelemetry/_opentelemetry_vertex/__init__.py
lilypad/_opentelemetry/_opentelemetry_vertex/patch.py
lilypad/_opentelemetry/_opentelemetry_vertex/utils.py
lilypad/_utils/__init__.py
lilypad/_utils/call_safely.py
lilypad/_utils/closure.py
python_lilypad-0.0.34.dist-info/METADATA
python_lilypad-0.0.34.dist-info/WHEEL
python_lilypad-0.0.34.dist-info/entry_points.txt
python_lilypad-0.0.34.dist-info/licenses/LICENSE
python_lilypad-0.0.34.dist-info/RECORD
