Metadata-Version: 2.4
Name: python-lilypad
Version: 0.0.34
Summary: An open-source prompt engineering framework.
Project-URL: Homepage, https://lilypad.so
Project-URL: Documentation, https://lilypad.so/docs
Project-URL: Repository, https://github.com/Mirascope/lilypad
Project-URL: Issues, https://github.com/Mirascope/lilypad/issues
Project-URL: Changelog, https://github.com/Mirascope/lilypad/releases
Author-email: William Bakst <william@mirascope.io>, Brendan Kao <brendan@mirascope.io>
Maintainer-email: William Bakst <william@mirascope.io>
License: Copyright (c) 2024-2025 Mirascope
License-File: LICENSE
Keywords: artificial intelligence,developer tools,evaluation,llm,llm tools,prompt engineering
Classifier: Development Status :: 3 - Alpha
Classifier: Framework :: OpenTelemetry
Classifier: Intended Audience :: Developers
Classifier: License :: OSI Approved :: MIT License
Classifier: Programming Language :: Python :: 3
Classifier: Programming Language :: Python :: 3.10
Classifier: Programming Language :: Python :: 3.11
Classifier: Programming Language :: Python :: 3.12
Classifier: Topic :: Scientific/Engineering :: Artificial Intelligence
Classifier: Topic :: Software Development :: Libraries
Requires-Python: >=3.10
Requires-Dist: cachetools>=5.5.1
Requires-Dist: datamodel-code-generator
Requires-Dist: httpx>=0.24.0
Requires-Dist: libcst>=1.6.0
Requires-Dist: mirascope>=1.20.1
Requires-Dist: opentelemetry-api>=1.30.0
Requires-Dist: opentelemetry-instrumentation>=0.51b0
Requires-Dist: opentelemetry-sdk>=1.30.0
Requires-Dist: pillow>=10.4.0
Requires-Dist: pydantic-settings>=2.6.1
Requires-Dist: pydantic>=2.0.0
Requires-Dist: requests>=2.32.3
Requires-Dist: rich>=13.0.0
Requires-Dist: ruff>=0.9.5
Requires-Dist: typer>=0.12.5
Requires-Dist: typing-extensions>=4.0.0
Provides-Extra: anthropic
Requires-Dist: anthropic>=0.36.0; extra == 'anthropic'
Provides-Extra: azure
Requires-Dist: aiohttp<4.0,>=3.10.5; extra == 'azure'
Requires-Dist: azure-ai-inference<2.0,>=1.0.0b9; extra == 'azure'
Provides-Extra: bedrock
Requires-Dist: aioboto3>=13.2.0; extra == 'bedrock'
Requires-Dist: boto3-stubs[bedrock-runtime]>=1.35.82; extra == 'bedrock'
Requires-Dist: boto3>=1.35.36; extra == 'bedrock'
Requires-Dist: types-aioboto3[bedrock-runtime]>=13.2.0.post3; extra == 'bedrock'
Provides-Extra: ee
Requires-Dist: cryptography>=43.0.3; extra == 'ee'
Provides-Extra: gemini
Requires-Dist: google-generativeai<1,>=0.4.0; extra == 'gemini'
Requires-Dist: pillow<11,>=10.4.0; extra == 'gemini'
Provides-Extra: google
Requires-Dist: google-genai<2,>=1.3.0; extra == 'google'
Requires-Dist: pillow<11,>=10.4.0; extra == 'google'
Provides-Extra: mistral
Requires-Dist: mistralai<2,>=1.0.0; extra == 'mistral'
Provides-Extra: openai
Requires-Dist: openai>=1.57.0; extra == 'openai'
Provides-Extra: outlines
Requires-Dist: outlines>=0.1.11; extra == 'outlines'
Provides-Extra: sandbox-docker
Requires-Dist: docker>=7.1.0; extra == 'sandbox-docker'
Provides-Extra: server
Requires-Dist: alembic-postgresql-enum>=1.6.0; extra == 'server'
Requires-Dist: alembic>=1.14.0; extra == 'server'
Requires-Dist: fastapi[standard]>=0.114.0; extra == 'server'
Requires-Dist: posthog>=3.8.3; extra == 'server'
Requires-Dist: psycopg2-binary>=2.9.9; extra == 'server'
Requires-Dist: python-jose[cryptography]>=3.3.0; extra == 'server'
Requires-Dist: resend>=2.6.0; extra == 'server'
Requires-Dist: sqlmodel>=0.0.22; extra == 'server'
Requires-Dist: starlette>=0.26.0; extra == 'server'
Provides-Extra: vertex
Requires-Dist: google-cloud-aiplatform>=1.74.0; extra == 'vertex'
